{
	"bannerUrl": "https://img-eshop.cdn.nintendo.net/i/cd3ebe3586d1f702aa7f73b30bce0cda1f22e6c86acf8b6d3598d9310b779af8.jpg",
	"iconUrl": "https://img-eshop.cdn.nintendo.net/i/300191c615484db8036f99f8e81cfbda6917ee9aea8546998f28648697df6f44.jpg",
	"publisher": "SAT-BOX",
	"screenshots": [
		"https://img-eshop.cdn.nintendo.net/i/ebdf591eae111584c80d4e254cb57cdedb16bce8038d77292bc77707446b2805.jpg",
		"https://img-eshop.cdn.nintendo.net/i/9624dc9792659ddd5b0ca8d5a5257f2e969f2c05c3fd2b99673b43d13ea6e4a5.jpg",
		"https://img-eshop.cdn.nintendo.net/i/bb0eb089ce8a282b99b638019245a42a7b86e5a798d90245017e541ac433d3be.jpg",
		"https://img-eshop.cdn.nintendo.net/i/4e0e8e604b185e7630d3f86337730f21ae59d079c30e7dd2e665c85647372a77.jpg",
		"https://img-eshop.cdn.nintendo.net/i/45c1ee3b233732e10799844bda54cb42cc1e566bc5b66e79efe5072ec2ca5392.jpg",
		"https://img-eshop.cdn.nintendo.net/i/5dbad525d2a9786ffc03d653ba1437c74d1671984053945b7b37ec96c1756762.jpg"
	],
	"releaseDate": 20250904,
	"category": [
		"Party",
		"Action",
		"Communication",
		"Sports"
	],
	"intro": "Get ready for a powered-up fishing trip to the vast ocean!\nWith stunning scenery and a wide variety of fish, the fishing is more thrilling and content-packed than ever!",
	"description": "Let's go fishing on the Nintendo Switch\u2122!\nTravel to 4 unique fishing spots\u2014including a rocky coast, seawall, fishing boat, and tropical pier\u2014where the fish you encounter change depending on the location and time of day!\nShare Joy-Con\u2122, and up to 4 players can join in!\nAim for a new high score!\n\n[Score Attack]\nCatch as many fish as you can within the time limit!\nLook out for big fish to boost your score!\nLook for the best lure and rod combo for each location!\n\n[Endless]\nSit back, relax, and enjoy endless fishing!\nWatch the scenery shift from day to night!\nChange your gear when the situation calls and keep an eye out for big fish!\n\n[Ranking]\nCompete against players around the world in Score Attack and Endless modes!\nShow off your skills by increasing your high score and rank!\n\n[Battle]\nFace off against CPUs in single-player mode, or test your skills against friends in multiplayer battles!\n\n[Shop]\nSpend the points you've earned from fishing to buy new lures and rods!\nFind your favorite lure/rod combination!\n\n[Records]\nEvery fish you catch will be recorded in your personal encyclopedia!\nCan you reel in every species and complete the collection?",
	"languages": [
		"ja",
		"en"
	],
	"numberOfPlayers": 4,
	"size": "861 MiB"
}