{
	"bannerUrl": "https://img-eshop.cdn.nintendo.net/i/634f69ef4b111869f04209889b828f89fcc012eea92a72307a5c8852ded44e42.jpg",
	"iconUrl": "https://img-eshop.cdn.nintendo.net/i/9150fe50fb273ddd58a8479a5a8fe012f9fa6591d47020e2eb9ed1a03b67959e.jpg",
	"publisher": "H2 INTERACTIVE",
	"screenshots": [
		"https://img-eshop.cdn.nintendo.net/i/fa08699a2395cdb24682237255d50cc126d2a5f1fc453d77de6debf54c484580.jpg",
		"https://img-eshop.cdn.nintendo.net/i/7ee8bc6d16437bc34bcfc08d137edcf4ed51c3ed6d40ac6276b5e53df20a82a3.jpg",
		"https://img-eshop.cdn.nintendo.net/i/24243fcafc645221e546c6581a096bdca40933e0125c747daeb411d63979c5c9.jpg",
		"https://img-eshop.cdn.nintendo.net/i/dd530a7a4507c76f0aadcc7d03ef00f886a742a764b3e4eb7a51b1f54028fe4d.jpg",
		"https://img-eshop.cdn.nintendo.net/i/ef8c51958d5ab151b8919dc3dca8809cacfa93dfa4e75aa6bd0451b2f9d2dc38.jpg",
		"https://img-eshop.cdn.nintendo.net/i/cbe6ad86ae054e0e836148da556ffc4e5c5939dbda2883599b901c251a741abf.jpg"
	],
	"releaseDate": 20190207,
	"category": [
		"\uaca9\ud22c",
		"\uc544\ucf00\uc774\ub4dc",
		"\uc561\uc158",
		"\uc5b4\ub4dc\ubca4\ucc98"
	],
	"intro": "\ubbf8\ub824\ud55c \uadf8\ub798\ud53d\uacfc \uc870\ud654\ub41c \uac8c\uc784 \uc2dc\uc2a4\ud15c\uc73c\ub85c, \uc804 \uc138\uacc4\uc5d0\uc11c \uc990\uae30\uace0 \uc788\ub294 2D \uaca9\ud22c \uac1c\uc804 \uac8c\uc784\uc758 \uacb0\uc815\ud310.",
	"description": "\ubbf8\ub824\ud55c \uadf8\ub798\ud53d\uacfc \uc870\ud654\ub41c \uac8c\uc784 \uc2dc\uc2a4\ud15c\uc73c\ub85c, \uc804 \uc138\uacc4\uc5d0\uc11c \uc990\uae30\uace0 \uc788\ub294 2D \uaca9\ud22c \uac1c\uc804 \uac8c\uc784\uc758 \uacb0\uc815\ud310.\n \u300cBLAZBLUE\u300d \uc2dc\ub9ac\uc988. \uadf8 \ucd5c\uc2e0\uc791\uc778 \u300cBLAZBLUE CENTRALFICTION\u300d\uc774 \ub4f1\uc7a5\ud569\ub2c8\ub2e4.",
	"languages": [
		"ja",
		"en",
		"ko",
		"zh",
		"zh"
	],
	"numberOfPlayers": 2,
	"size": "11.76 GiB"
}