{
	"bannerUrl": "https://img-eshop.cdn.nintendo.net/i/fe12c895cd678a18fa2f7d5b4baa158f24d4263e6ee925d02a1baee30e5a5612.jpg",
	"iconUrl": "https://img-eshop.cdn.nintendo.net/i/c9b2fefed36366c7e29be3317e3b2c6d8dcdf582335ea0217405025ac155c3ca.jpg",
	"publisher": "Microids",
	"screenshots": [
		"https://img-eshop.cdn.nintendo.net/i/ad73f911859f6d3b918eb499ea4c5321fa49c07be009d614e4d24f5a80765241.jpg",
		"https://img-eshop.cdn.nintendo.net/i/29946c523e758995695dd621db8c5886db6a67b81cdeb346f4775e884433b630.jpg",
		"https://img-eshop.cdn.nintendo.net/i/21f39cb5b430e074072c7c6163e43de5fcb68a6e4f3b0840924529f72bbb7b69.jpg",
		"https://img-eshop.cdn.nintendo.net/i/35d554300dc5b07449098cc5029752202b4cb840f131e744d53c9b6c3f7d68c5.jpg",
		"https://img-eshop.cdn.nintendo.net/i/bfbe7a7f7907c82005582a99d0d0f710aa760cd073fd48adc3fec7fcb746c06c.jpg"
	],
	"releaseDate": 20230629,
	"category": [
		"RPG"
	],
	"intro": "Lead a team of adventurers to the highest rank of all guilds!",
	"description": "Follow Baster the Neogician, Drek the Berserker, May the Cartomancer and Logs the Elementalist in their quest for the supreme level, and help them reach their Legendary Class to become part of the elite of the Horizon MMORPG!\n\nFace hundreds of monsters and wander around fantastic worlds to give your guild the place it deserves in the world of Olydri, among the mythic Noob, Justice, Roxxor and Pro Game Master guilds.\nBut the challenge you will face will not be limited to Horizon: your avatars will accomplish \u00ab real \u00bb quests in real life. History can be made both into the game and IRL!\n\nDo you have what it takes to get your team to level 100?\n\nGENERAL INFORMATION\n- Embody a team of 4 hardcore gamers and their video game avatars in a challenging and colorful RPG in a homage to the greatest J-RPGs!\n- Explore a huge world, fight intense battles and complete quests to level up your team\n- Customize your avatars with the best equipment you will loot in dungeons, grottos, chests and city shops!\n- Strengthen your team and upgrade your abilities by farming experience through the fights: adapt your skills to your fighting style or to the foes you encounter\n- Browse the world of Olydri and make your mark among the most powerful factions of the \u201cHorizon\u201d MMORPG, where the greatest players meet and fight!\n- Play the \u201creal\u201d players in the \u201creal world\u201d and find out who is behind your friends\u2019 avatars\u2026 or your enemies\u2019!\n\nSPECIAL FEATURES\n- An appealing graphic direction and \u201cchibi\u201d vibe as a homage to the greatest J-RPGs\n- A true RPG experience with 50+ hours of gameplay, 750+ avatars to interact with and 300+ maps to wander in",
	"languages": [
		"en",
		"es",
		"fr",
		"de"
	],
	"numberOfPlayers": 1,
	"size": "7.09 GiB"
}