{
	"bannerUrl": "https://img-eshop.cdn.nintendo.net/i/9202586fd382c112660079bcd7dfa948eefb7b141597dac679508adb9fd3c104.jpg",
	"iconUrl": "https://img-eshop.cdn.nintendo.net/i/c52bac2f88d9513fc231963492affea0f46eb4c763205c4f8456c0e29b2ffbe3.jpg",
	"publisher": "Sometimes You",
	"screenshots": [
		"https://img-eshop.cdn.nintendo.net/i/130421f330c5208f222fa7825779f8808d2c9eb757b14e7af05db122db8a7000.jpg",
		"https://img-eshop.cdn.nintendo.net/i/3a6f26b89114a4b9c748e2a23e4c55fe426a7bbbaa23e04c675ad6dbf3646795.jpg",
		"https://img-eshop.cdn.nintendo.net/i/ed80d4602a3c8da3c38f8b8cbb3470c078268d2bd4defc26a644f4ec9171d3a6.jpg",
		"https://img-eshop.cdn.nintendo.net/i/2d314c7673593ab47a755d5fa708874637949b60b79de49743ee179c3e587258.jpg",
		"https://img-eshop.cdn.nintendo.net/i/68cf581330766e0b35e477ecf4cc7f20958d400ad4829df0af04a8a3b82ed9d7.jpg",
		"https://img-eshop.cdn.nintendo.net/i/2da415c1ca4aab95c07242fd0925146c1c72bbae6b7b76346ff5511ecd43a5a2.jpg"
	],
	"releaseDate": 20260529,
	"category": [
		"Adventure",
		"Puzzle"
	],
	"intro": "A dark point-and-click adventure where you will dive into a world of eerie fairy tales",
	"description": "Midnight Swamp is a dark point-and-click adventure where you will dive into a world of eerie fairy tales. Play as a tourist who must find a way out of a mysterious swamp, where every corner hides a riddle.\n\nA mysterious laugh echoed from the lake on that restless summer night. One careless step outside the tent \u2014 and you find yourself dragged into a dark world of shifting swamps, inhabited by strange creatures and filled with hidden secrets.\n\nSoon, a talking Cat convinces you to enter the inhospitable castle rising above the swamp, while the Witch from the gingerbread house teaches you the basics of potion brewing. Will you have the courage to uncover the mystery of this place?\n\nFeatures:\n- A variety of puzzles, potion crafting, and location exploration\n- A dark swamp hiding a sinister secret\n- Many strange inhabitants for you to meet\n- Hand-drawn graphics",
	"languages": [
		"en",
		"pt",
		"de",
		"ru"
	],
	"numberOfPlayers": 1,
	"rating": 13,
	"ratingContent": [
		"Blood",
		"Use of Tobacco",
		"Violence"
	],
	"dlcs": [],
	"size": "917 MiB"
}