{
	"bannerUrl": "https://img-eshop.cdn.nintendo.net/i/d056d2c6aad99d1b7ac1c426afb1e7349a7b11ae4b9734d4e77c7620fb93976d.jpg",
	"iconUrl": "https://img-eshop.cdn.nintendo.net/i/06a78895e2b70cc504e4a41faaafa61a389c2c38a6c933f4d300aadf1991e944.jpg",
	"publisher": "Chucklefish",
	"screenshots": [
		"https://img-eshop.cdn.nintendo.net/i/20f49a6e5caccb424fd77616b1ac6d344f432169fd67f4485214d6c153829584.jpg",
		"https://img-eshop.cdn.nintendo.net/i/2a5dca8d6e9524c0959b8003ee96182f670c3dbb70b2b657f1c2587002551c9f.jpg",
		"https://img-eshop.cdn.nintendo.net/i/597f0ac5321766ff05f40ca2d02b1b0565fa24d98026192e3ed8ded123a70c57.jpg",
		"https://img-eshop.cdn.nintendo.net/i/01ce71023e9f808b1ca1da494dd8b95d6c1c14eb991573404c281dcc09a51c4a.jpg",
		"https://img-eshop.cdn.nintendo.net/i/af5d94f7878d375d4e67a9eba5d08c3e39cdb8cb8b4799af61998a985ee9dddf.jpg",
		"https://img-eshop.cdn.nintendo.net/i/f4dfef3f471e37aae67d96a5ade3a55aa8a22bdb2cc4d35971adb4cec8ae53e4.jpg"
	],
	"releaseDate": 20230412,
	"category": [
		"Strategy",
		"Adventure"
	],
	"intro": "A deck to weather the storm",
	"description": "Take on the elements in Wildfrost, a tactical roguelike deckbuilder! \n\nThe sun has frozen over, succumbing to the Wildfrost. The town of Snowdwell and its survivors stand as the last bastion against an eternal winter... Build up a deck of powerful card companions and elemental items, as you battle to banish the frost once and for all!\n\n\u2022 Perfect your card battling skills and craft a deck unique to you, as you journey across an unforgiving frosty landscape.\n\n\u2022 Collect and upgrade card companions, ready to withstand waves of deceptively cute Pengoons, Gobblers and brutish boss monsters. \n\n\u2022 Plan ahead in battles with the help of a dynamic counter system to map out your next move and fend off frosty foes.\n\n\u2022 Upgrade and customise your favourite companions with wobbly charms to enhance their powers.\n\n\u2022 Take shelter in the town of Snowdwell between runs, constructing buildings to unlock new cards, tribes, events and more to aid in your fight against the everlasting frost. \n\n\u2022 Test your skills with daily runs and challenges, creating endless replayability!",
	"languages": [
		"ja",
		"en",
		"ko",
		"zh",
		"zh"
	],
	"numberOfPlayers": 1,
	"size": "729 MiB"
}