{
	"bannerUrl": "https://img-eshop.cdn.nintendo.net/i/678e20561a1bf31dd541a2c5564b6642fd1eb175fcf2d6007727873e80ab149d.jpg",
	"iconUrl": "https://img-eshop.cdn.nintendo.net/i/cc3f449953826312c48ca47c9fce40ae28ada3f5ad9baebb1f3065f703980fe1.jpg",
	"publisher": "Asylum Square Interactive",
	"screenshots": [
		"https://img-eshop.cdn.nintendo.net/i/04c18a1051dd4da307a5f043966e2eb5ac508034ccc6aecd75b2eb7386d40778.jpg",
		"https://img-eshop.cdn.nintendo.net/i/22b8dc6d2c14677d22ddbdacaf6a4177f56e9c961a95fe7c01b2148e533654a0.jpg",
		"https://img-eshop.cdn.nintendo.net/i/dafeeb5715b5b178b3f8a2fba2f5e7f9e6b264f4fd2bdfdeab0723354bd2f894.jpg",
		"https://img-eshop.cdn.nintendo.net/i/d42766661eed149d8992e92987fab2f37f55795056c0ad58abf72e9636d0f70b.jpg",
		"https://img-eshop.cdn.nintendo.net/i/1f8039d5e873e42afdc0ae970b7749235566df943efa1a8e25edcacfc6a72b9c.jpg",
		"https://img-eshop.cdn.nintendo.net/i/174e0d80c465d88bbc5f12b7b271db16395fc5bea69a644f2440fdf2d19ffa4d.jpg"
	],
	"releaseDate": 20220205,
	"category": [
		"Board Game",
		"Strategy",
		"Puzzle",
		"Other"
	],
	"intro": "The puzzle game\nthat challenges your mind!",
	"description": "Play Pirate's Gold today and get ready for one of the greatest pirate puzzle adventures of all time. Experience an exciting journey through the Caribbean and plunder 100 treasure caves.\n\nEach cave is a puzzle that demands everything from your logical thinking skills. Move the precious items around to make pairs. Find the right strategy to avoid obstacles or use one of the many magic items. Use the bomb to blow up unpleasant objects or use the sword to remove obstacles that get in your way. Analyze the tricky arrow mazes to find all the pieces of the cursed amulet and become the most feared pirate of the Caribbean.\n\nAre you clever enough to find all the treasures?",
	"languages": [
		"en",
		"de"
	],
	"numberOfPlayers": 1,
	"size": "82 MiB"
}