{
	"bannerUrl": "https://img-eshop.cdn.nintendo.net/i/2bbb5673a82170af9ded1ce80ce8b12c0c7463b9720738c56cf40dee945b6e9f.jpg",
	"iconUrl": "https://img-eshop.cdn.nintendo.net/i/9737ec203edc400b6962d599b9888ab37b195f4675af11af3edae9c1fa36ebb4.jpg",
	"publisher": "eastasiasoft",
	"screenshots": [
		"https://img-eshop.cdn.nintendo.net/i/5066e2be211e84c5d8779054ac1d5fb3dcffcb38e88a467620b24abc4433f5d9.jpg",
		"https://img-eshop.cdn.nintendo.net/i/c08a3faa5159c91d00913ac18678aff7aa6b7f9891e6817df45e74fc4eb77e15.jpg",
		"https://img-eshop.cdn.nintendo.net/i/c4751cfe2e3b12eb586f98b5637fc40a7756fb41b0d993f65093d6cce7d5700e.jpg",
		"https://img-eshop.cdn.nintendo.net/i/f3e10881a24a6259bb848716a907bfa93cc87345cd72eccb85167330110839f5.jpg",
		"https://img-eshop.cdn.nintendo.net/i/2fabf52343d00f9209019e355ca908dd4dec5c53e6e3f39223ac7d4467887ca3.jpg",
		"https://img-eshop.cdn.nintendo.net/i/96a0a8f76af31cb67d72149b995813015e20b94df70866563bfe0c0689a08844.jpg"
	],
	"releaseDate": 20251029,
	"category": [
		"Platformer",
		"Arcade",
		"Action",
		"Adventure"
	],
	"intro": "Face classic horror monsters and retrieve your stolen pumpkins in retro arcade style!",
	"description": "Step into the arcade-era thrill of Halloween 1985!\n\nWhen monsters steal Pumpkman\u2019s pumpkins on Halloween night, it\u2019s up to you to get them back! Dash through 5 vibrant, quirky levels, outsmarting classic foes like Dracula, The Mummy, and The Witch. Jump, dodge, and battle your way to their lairs, then take on the big boss in a final showdown!\n\nWith 3 game modes, a retro chiptune soundtrack, and high-score chasing just like the golden age, this pixel-art platformer delivers fast-paced, nostalgic fun.\n\nCan you reclaim all the pumpkins and become a legend?\n\n\u2022 Master 5 Halloween-themed platforming stages.\n\u2022 Run, jump and dodge as Pumpkman.\n\u2022 Choose from multiple difficulty settings.\n\u2022 Take down monstrous bosses.\n\u2022 Chase high scores in old-school arcade style.\n\u2022 Enjoy retro pixel art graphics and a chiptune soundtrack.",
	"languages": [
		"ja",
		"en",
		"es"
	],
	"numberOfPlayers": 1,
	"size": "163 MiB"
}