{
	"bannerUrl": "https://img-eshop.cdn.nintendo.net/i/0d045f91316ecdced1f7965baa1916ba72da9e7e7e91116fddf432b7786a1793.jpg",
	"iconUrl": "https://img-eshop.cdn.nintendo.net/i/5c9c7aa9da05687955e5b66db64054b10c7e2ef97e4dd724afaf4cbc9f56cd1e.jpg",
	"publisher": "INVECTOR GAME STUDIO",
	"screenshots": [
		"https://img-eshop.cdn.nintendo.net/i/7ddb835193c0ddd66d8247ccdd842d3206d1525ca7901c27d2a6649df9c1c419.jpg",
		"https://img-eshop.cdn.nintendo.net/i/88111bea9d02a7b8dd35c0397abc9d4e9104daf0efd6dc6292395b19466ec493.jpg",
		"https://img-eshop.cdn.nintendo.net/i/3b22098a649cca6f9d928af3edb3e74c9e838ee660b147d1c274bd7739c19c75.jpg",
		"https://img-eshop.cdn.nintendo.net/i/eb971d2cf3c0c212c75713766704cfc217bf72483dc3cf1b46182ae06085d118.jpg",
		"https://img-eshop.cdn.nintendo.net/i/91db81e9a1ca886af88bdd77d4d9ed8323767ce86a197fb9bb8ace71594ec948.jpg",
		"https://img-eshop.cdn.nintendo.net/i/af1c9961fc6006ef9ccbf9a07da21396a12a224714bc89edbdfbf8467f226bb1.jpg"
	],
	"releaseDate": 20251009,
	"category": [
		"Arcade",
		"Action",
		"Adventure",
		"RPG"
	],
	"intro": "Pilot upgrade and conquer in the ultimate sci fi mech warfare experience\nFight on Mars and the Moon.",
	"description": "Robot Warfare: War Game puts you in command of powerful combat mechs in intense sci-fi battles across diverse arenas. Built on a mech combat system, the game expands with brand-new maps including a futuristic base, the surface of Mars, the Moon, and other science-fiction battlefields.\n\nPlayers can choose from a roster of unique robot characters, each customizable and upgradeable with different weapons and abilities. As you progress through missions on each map, you\u2019ll unlock new upgrades, challenges, and progression paths that reward both strategy and skill.\n\nWith fast-paced mech battles, deep customization, and a variety of environments, Robot Warfare: War Game delivers an action-packed experience for fans of robot combat and futuristic warfare.",
	"languages": [
		"en"
	],
	"numberOfPlayers": 1,
	"size": "1.42 GiB"
}