{
	"bannerUrl": "https://img-eshop.cdn.nintendo.net/i/46e9986bdc922c70e499ebe4b6cfe883560449725b09b4e146f5fb18639211e2.jpg",
	"iconUrl": "https://img-eshop.cdn.nintendo.net/i/c7dfeff402203b6763b1ae50e02a501ffe069733eddd62721f00e6fc4ab4d294.jpg",
	"publisher": "Nerd Games",
	"screenshots": [
		"https://img-eshop.cdn.nintendo.net/i/f4c2409d53485dd304b6f22f999acb1a5f64c40b187e73ef6bf22990ffbac900.jpg",
		"https://img-eshop.cdn.nintendo.net/i/04f444a35c8d1de24bf5a4f64aeb36fded9a2cebbb35f0793e184423f63b8215.jpg",
		"https://img-eshop.cdn.nintendo.net/i/a689b566c5171670ce39946420521bcace8ec2e4ac5b1a815b9c3513d5c658b6.jpg",
		"https://img-eshop.cdn.nintendo.net/i/72a359a640dc9be4bced84e8b56631e28cc4b31f550827c8f1bf43d6c40b3532.jpg"
	],
	"releaseDate": 20241228,
	"category": [
		"Adventure",
		"Platformer"
	],
	"intro": "In this thrilling adventure, help Bill, a humanoid cat, restore peace to his village after a devastating attack.",
	"description": "Felinea Tales is a captivating 2.5D platformer where players step into the paws of Bill, a brave and agile cat. After the peaceful village of Felinea falls victim to the sinister experiments of the wizard Abyssius, Bill sets out on an epic journey to restore order and save his home.\n\nJump, fight enemies, and dodge dangers as you help Bill seek justice. Explore diverse worlds filled with challenges, secrets, and exciting adventures.\n\nDesigned to appeal to players of all ages, Felinea Tales offers an unforgettable adventure with nostalgic charm and a modern twist, making it a perfect choice for fans of adventure games and immersive storytelling. \n\nAre you ready to help Bill bring justice to Felinea?",
	"languages": [
		"en",
		"pt"
	],
	"numberOfPlayers": 1,
	"size": "325 MiB"
}