{
	"bannerUrl": "https://img-eshop.cdn.nintendo.net/i/77f4d5cfe7aabd88546060f8e6fca45c25778f53e2c65308348a4506c7dc851b.jpg",
	"iconUrl": "https://img-eshop.cdn.nintendo.net/i/8540e181cecfa0230318c1e19447d5a75c34f560709fe9f3618c882d8d07de66.jpg",
	"publisher": "HAMSTER",
	"screenshots": [
		"https://img-eshop.cdn.nintendo.net/i/0913e5108699f569408c3def345daf50e41a4947785db4f48e8a15fb656dc5f1.jpg",
		"https://img-eshop.cdn.nintendo.net/i/90ba8f048761f2c040edf8c250e6ab8222b301f6c9ae3db582112107b7d2423b.jpg",
		"https://img-eshop.cdn.nintendo.net/i/aaf98f2244d798b8f39165b13467558d9c7ac96dc71020ac17466f2c1a935b53.jpg",
		"https://img-eshop.cdn.nintendo.net/i/3f5778c5a558b2c4f22852bde04b4cc475ef4b3957a2e9f6e8fdaf1695f13b7f.jpg",
		"https://img-eshop.cdn.nintendo.net/i/fcacec8fec71063fa5a1eb444af9ba41b00e24571ded00bb568bd2e7c5f48e83.jpg",
		"https://img-eshop.cdn.nintendo.net/i/dee12eb103106cbb3016996959aeb766c7e5829c903e4ff81d942d7cc9f3814f.jpg"
	],
	"releaseDate": 20241107,
	"category": [
		"Action",
		"Arcade"
	],
	"intro": "Let's take back the BLUE CRYSTAL ROD, \na symbol of love and peace!",
	"description": "\" VS. The Quest of Ki \" is an action game released by NAMCO (Bandai Namco Entertainment) in 1988.\nThe objective of the game is to recover the BLUE CRYSTAL ROD that has been stolen by DRUAGA.\nThe main character, KI, is controlled to reach the top of the tower where monsters are roaming around.\n\nThe \"Arcade Archives\" series has faithfully reproduced many classic Arcade masterpieces.\nPlayers can change various game settings such as game difficulty, and also reproduce the atmosphere of arcade display settings at that time. Players can also compete against each other from all over the world with their high scores.\nPlease enjoy the masterpiece that built a generation for video games.\n\n*This game uses the Japanese ROM for the main part of the game.\n*The options menu and manual are available in Japanese, English, French, German, Italian, and Spanish.",
	"languages": [
		"ja",
		"en",
		"es",
		"fr",
		"de",
		"it"
	],
	"numberOfPlayers": 1,
	"size": "156 MiB"
}