{
	"bannerUrl": "https://img-eshop.cdn.nintendo.net/i/d241fc4627db5701308c42c433957b0845f45e8624013e2b50afb43a2d15b8b5.jpg",
	"iconUrl": "https://img-eshop.cdn.nintendo.net/i/9ab0b00d282c8dc31840d3127c0934989a7b9e0050b32d95e11e6b96d83dea27.jpg",
	"publisher": "inXile Entertainment",
	"screenshots": [
		"https://img-eshop.cdn.nintendo.net/i/1485cbe1d9a2443c778521a8f8b317481891049c05f54b2fda75597f3bac0f7b.jpg",
		"https://img-eshop.cdn.nintendo.net/i/ec0359626a9d8d385d21f6264dddf1c646dc49b9950b8a4fb249bc4146a5b4eb.jpg",
		"https://img-eshop.cdn.nintendo.net/i/7e667d4085b252a2f75314a0093e044b1d7b870b2ba960e2bcc0aee9fcb87e06.jpg",
		"https://img-eshop.cdn.nintendo.net/i/6d3b785e29c9479cf9f2b4d6d4bf0e788476b410aa18781755be6fc542a5ecc0.jpg",
		"https://img-eshop.cdn.nintendo.net/i/8f9e41abb9d246321267fb53a870569e245af036130d4119d8ea23e2b27e88f5.jpg",
		"https://img-eshop.cdn.nintendo.net/i/c63240529e8d30a740af5c22e39448c7a3222fcc0f7d6f918722591368d0bf3f.jpg"
	],
	"releaseDate": 20200617,
	"category": [
		"Action",
		"RPG",
		"Adventure",
		"Other"
	],
	"intro": "You are the Bard, a selfish rogue weary of pointless sub-quests and rat-infested cellars. Through magical song you summon characters to join your quest!\n\nPrepare to immerse yourself in over 20-30 hours of adventure, featuring: \n\u2022 50 enemy types (not counting bosses!) \n\u2022 A vast world to explore with towns, wild forests, rivers, castles, towers, secret dungeons, snowy mountains, caverns, haunted tombs and more.\n\u2022 A full cast of bizarre NPCs.\n\u2022 Over a dozen special boss enemies to defeat. \n\u2022 16 magical characters to discover and then summon at will to aid you.\n\u2022 Over 150 unique items of weaponry, armor, instruments, tokens, artifacts and loot! \n\u2022 More Song & Dance numbers than any other game, including a zombie dance-off! \n\u2022 Over 14 hours of outstanding voice-acting from top Hollywood talent, including Cary Elwes (The Princess Bride) as the Bard, and the inimitable Tony Jay as the Narrator.",
	"languages": [
		"en",
		"es",
		"fr",
		"de",
		"it",
		"ru"
	],
	"numberOfPlayers": 1,
	"size": "3.59 GiB"
}