{
	"bannerUrl": "https://img-eshop.cdn.nintendo.net/i/67136ae892e6addebce79a3c0ba2707c126e478917219b2aaee81f02283b77d8.jpg",
	"iconUrl": "https://img-eshop.cdn.nintendo.net/i/9b857226f253788a8b447c7f07054eee6a01a1e3d13972106f76c522b9c28ef9.jpg",
	"publisher": "GOGAME CONSOLE PUBLISHER",
	"screenshots": [
		"https://img-eshop.cdn.nintendo.net/i/3f6dd18801ee3fac3279de49380f760186f8d28ccc04caab23176598a22fca23.jpg",
		"https://img-eshop.cdn.nintendo.net/i/3a0464f1049c3553bc25f42a9de04713022434f99f451fea26dad2be5f836d65.jpg",
		"https://img-eshop.cdn.nintendo.net/i/d8e832633e7efd5c13df80bf5872a5e28d77ce936c9d49357f117efc1f9faa0c.jpg",
		"https://img-eshop.cdn.nintendo.net/i/54e84133d507fae98d98b0ac870565bbb33b6889b931b931237877b6a8cd65fd.jpg",
		"https://img-eshop.cdn.nintendo.net/i/ae17be4016a2d5224598f0b71ab96c082391fba059dee00ed80b0be1c1ac952e.jpg",
		"https://img-eshop.cdn.nintendo.net/i/25d804817e0738f110f5d0024a4e0c5e02f873086a9c50f775c3d74d54ec10e5.jpg"
	],
	"releaseDate": 20231221,
	"category": [
		"Adventure",
		"Simulation",
		"Strategy",
		"RPG"
	],
	"intro": null,
	"description": "Embark on an exhilarating journey in our food delivery adventure game - Bike Courier: Bistro Express Delivery, where you take on the role of a dynamic delivery cyclist navigating the bustling streets of the city. As the main character, your mission is clear: hop on your trusty bicycle, visit various restaurants to collect orders, and ensure their safe and timely delivery to hungry customers.\n\nAs you pedal through the vivid cityscape, each delivery presents a unique challenge. Race against time to pick up orders from a range of restaurants, carefully securing them in your delivery bag to ensure they arrive at their destination in perfect condition. Precision is key, and every decision counts as you navigate through busy streets, avoiding potential obstacles and challenges that could jeopardize the integrity of your delivery.\n\nBut the excitement doesn't end there. Customize your delivery experience by choosing from a variety of bicycles and personalizing them to match your style. \nExplore a myriad of locations, each with its own distinct charm and beauty. From bustling downtown areas to serene villages, every location presents a visual feast for your eyes as you pedal through a world filled with diverse landscapes and landmarks.\nHowever, the journey isn't without its risks. Penalties await those who aren't cautious enough to avoid collisions with cars, pedestrians, and other potential hazards. Maneuver through the bustling streets with finesse, showcasing your skills as the city's premier food delivery cyclist.\nAre you up for the challenge? The city awaits, and every delivery is a chance to showcase your prowess in the art of culinary transport. Get ready to pedal your way to victory in - Bike Courier: Bistro Express Delivery!",
	"languages": [
		"en"
	],
	"numberOfPlayers": 1,
	"size": "1.47 GiB"
}