{
	"bannerUrl": "https://img-eshop.cdn.nintendo.net/i/a75bb88fe4b48567bed1e601d9f6afd4f4dd72344087ec7d50d0f843fd55cc42.jpg",
	"iconUrl": "https://img-eshop.cdn.nintendo.net/i/7b5675a5496fc620f37915b11041fbba4ba0140e4d783babfe730f5fe0aad65c.jpg",
	"publisher": "Square Enix Europe LTD",
	"screenshots": [
		"https://img-eshop.cdn.nintendo.net/i/d97e7bb383daaabfc491ede706136985ee22d4059ea608af97917113868e1c3b.jpg",
		"https://img-eshop.cdn.nintendo.net/i/93ca736a848ca36e7c3313b5f1e5975579bf51b0548561f6d0271e905675906a.jpg",
		"https://img-eshop.cdn.nintendo.net/i/ecc38ed5a9fa8d126a6d14973a721c35c35f8676ca7cac586c609a7e6f116fec.jpg",
		"https://img-eshop.cdn.nintendo.net/i/d65c6908a505bb55745fc4ee64507740ceece6a3b21379a410fe7e2056a1c856.jpg",
		"https://img-eshop.cdn.nintendo.net/i/164034f762d06aebdd119f909c54c58d25b0da99463956b4c350d08428beda68.jpg",
		"https://img-eshop.cdn.nintendo.net/i/1666c126783f631783721fcd8c23005a40a69fcecb61efa5d573085a5625b567.jpg"
	],
	"releaseDate": 20200207,
	"category": [
		"Puzzle",
		"Strategy"
	],
	"intro": "The Turing Test is a first person puzzler that explores the phenomena of consciousness and challenges the meaning of human intuition.",
	"description": "The Turing Test is a challenging first-person puzzle game set on Jupiter\u2019s moon, Europa. You are Ava Turing, an engineer for the International Space Agency (ISA) sent to discover the cause behind the disappearance of the ground crew stationed there. Guided only by the station\u2019s AI, Tom, find your way through the facility and discover what it truly means to be human.\n\n\u2022 Harness the ability to transfer power between machines using your \u2018Energy Manipulation Tool\u2019 providing a unique twist on gameplay mechanics and puzzle logic.\n\u2022 Learn the significance of player control as you switch between multiple perspectives to solve The Turing Test\u2019s most challenging puzzles.\n\u2022 Discover a story with multiple layers of depth and conspiracy; challenging concepts of human morality and giving freedom to players to form theories about the fate of ISA's crew members.",
	"languages": [
		"en",
		"es",
		"fr",
		"de",
		"it"
	],
	"numberOfPlayers": 1,
	"size": "2.80 GiB"
}