{
	"bannerUrl": "https://img-eshop.cdn.nintendo.net/i/2228f268003a3bcc5c2e8be4d7a1d6780b4f1aa8cee45d94cfc1f7b124f31e0f.jpg",
	"iconUrl": "https://img-eshop.cdn.nintendo.net/i/652b689fdcf8b03aa47ad0c19f1d27395cf7bf5aae8b096a25964ba39faf5a3d.jpg",
	"publisher": "Parallel Circles",
	"screenshots": [
		"https://img-eshop.cdn.nintendo.net/i/ad29a51b9e9e62122afbe3aa784c77c5056186fd075d577bf497a249d3a6f194.jpg",
		"https://img-eshop.cdn.nintendo.net/i/72d8801282b3d91f14590f9eeeee02e6765f03bb06b02ba27b00295a1fd849c5.jpg",
		"https://img-eshop.cdn.nintendo.net/i/35e18236fb1675b4bf2be9d6c05acfcb3a3b5ea5b6ccd0b455efab30902e6f97.jpg",
		"https://img-eshop.cdn.nintendo.net/i/5afb823c08fcdb38ada11b8b29313b1a3b8ab73293cf8d2a9919b4c158455bd2.jpg",
		"https://img-eshop.cdn.nintendo.net/i/25afffb909c77e458933bbe24068c407b3d92ffcf0c630f8f441c7650ae0a59e.jpg",
		"https://img-eshop.cdn.nintendo.net/i/b5ecad95811d6e34779cb9aff240dc61b27b647de0d18435021e90ec8fb5f417.jpg"
	],
	"releaseDate": 20180802,
	"category": [
		"Action",
		"Arcade",
		"Party",
		"Platformer"
	],
	"intro": "Dodge, jump, and dash your way through hundreds of terrifying geometric levels. Too tough? Bring your friends.",
	"description": "When was the last time you felt like a hero? Flat Heroes rewards you with that good old feeling of surviving impossible levels alongside a smooth modern design with a minimalist style. With a simple set of movements \u2014 Run. Jump. Dash. Attack. \u2014 and delightful controls, Flat Heroes encourages you to stylishly navigate and survive over 300 handcrafted levels, destroy the most epic bosses around and truly be the two-dimensional hero (or heroes!) you\u2019ve always dreamed you could be.\n\nEasy to learn and hard to master; it is easy to pick up and even easier to learn, but don\u2019t let that fool you! During your adventure you will face increasingly difficult challenges that will require you to master the game\u2019s controls on the journey to becoming a true Hero. And while Flat Heroes comes along with a very minimalistic art style, it\u2019s spiced up with stunning effects making it one truly unique eye candy experience.\n\nGot stuck in the campaign or want to survive longer in the challenge modes? Too intense for you to take on alone? Let your friends join the party; Flat Heroes is the perfect couch co-op experience! Invite a few friends, get some pizza and overcome the challenges together!\n\nKey Features:\n*Play alone or share the experience with up to 4 friends on all modes\n*Drop in & Drop Out Co-Op\n*More than 300 Levels\n*Face 10 unique final Bosses\n*Unlimited survival Levels, with daily challenges and Leaderboards\n*Versus Modes offer you and your friends an option to compete against each other",
	"languages": [
		"ja",
		"en",
		"es",
		"fr",
		"de",
		"it",
		"nl",
		"pt",
		"ru",
		"ko",
		"zh",
		"zh"
	],
	"numberOfPlayers": 4,
	"size": "241 MiB"
}