{
	"bannerUrl": "https://img-eshop.cdn.nintendo.net/i/f56f77fef4133eb31f9ef9089427a4a38046d259d155459555fa6b77b80a3428.jpg",
	"iconUrl": "https://img-eshop.cdn.nintendo.net/i/4a6d5309f767c1a1f43a6beda7501d449269f743073fd8fd32d99313b30cc73f.jpg",
	"publisher": "BoggySoft",
	"screenshots": [
		"https://img-eshop.cdn.nintendo.net/i/c55444a43c5b35b3e5f83c1e150f4db2061eaadd3d867d1a27de02255e4ef32d.jpg",
		"https://img-eshop.cdn.nintendo.net/i/90ab0f31b115e3b1ca0f679b0b65b4b1ce8cbb21589f5945a5ce01b47b61df70.jpg",
		"https://img-eshop.cdn.nintendo.net/i/cce2b0a004e969660e6214662641f6f48ca73874088aaf0c72dab4900206f589.jpg",
		"https://img-eshop.cdn.nintendo.net/i/c2aadbfa1b0e68dbbd1709e85931402888c8955f4830310f6dfeaffa9f29db08.jpg",
		"https://img-eshop.cdn.nintendo.net/i/9e2c47ed8ba683df8e07fe3036281bee42e3ece61b59c61bd0ecebaeac2bd787.jpg",
		"https://img-eshop.cdn.nintendo.net/i/857b9bc634bf00972ac4b3c31a1f81996142945a62a35347ea98eccdf63be094.jpg"
	],
	"releaseDate": 20251007,
	"category": [
		"Strategy",
		"Simulation",
		"Shooter",
		"Action"
	],
	"intro": "Fight the undead and conquer chaos in a shattered world.",
	"description": "Survival Zombie is an intense survival experience set in a post-apocalyptic world, where players are pushed to their physical and mental limits in a relentless fight to stay alive. In a land dominated by the undead, quick thinking, smart strategies, and teamwork with other survivors can mean the difference between life and death.\n\nKey Features:\n \u2022 Thrilling exploration: Roam abandoned cities, shadowy forests, and hidden bunkers teeming with resources\u2014and unexpected dangers.\n \u2022 Perpetual threats: Zombies aren\u2019t the only danger. Other survivors, wild animals, and harsh environmental conditions can strike without warning.\n \u2022 Craft and survive: Collect resources, craft improvised weapons, and build secure shelters to protect yourself from waves of enemies.\n \u2022 Tough moral choices: Confront challenging scenarios where every decision carries lasting consequences.\n \u2022 Evolving undead: Each day brings smarter, deadlier zombies, keeping you on constant alert.\n\nAre you prepared to confront fear, make life-altering choices, and endure in Survival Zombie? Adventure awaits\u2014but only the cunning and resilient will survive!",
	"languages": [
		"en"
	],
	"numberOfPlayers": 1,
	"size": "885 MiB"
}