{
	"bannerUrl": "https://img-eshop.cdn.nintendo.net/i/99d7ba00b6cbb4a3427e1d237cd65f2e7b780eed5d12e101bd3e30cb75083946.jpg",
	"iconUrl": "https://img-eshop.cdn.nintendo.net/i/79d61fb49f7a856f3079cb24034c39d6b86c5b8a0fe206b00656c2c81fd6a8bd.jpg",
	"publisher": "QUByte Interactive",
	"screenshots": [
		"https://img-eshop.cdn.nintendo.net/i/6e61700233034d87897f4d45516ef42c78b75c7a70d58e4c9d7faff8799e3f68.jpg",
		"https://img-eshop.cdn.nintendo.net/i/770857d9f98b5ec46e246247cfa9608d1362cf2f765a5a4a4ae782eabd102a37.jpg",
		"https://img-eshop.cdn.nintendo.net/i/00d9d5c748989a6469145b374633748f892e715bc1ce9adf1d5e08034526a65b.jpg",
		"https://img-eshop.cdn.nintendo.net/i/4aaeed3cdf850a51e281ae1b433b2e36bf1a58d7b32913f37756a0265f447489.jpg",
		"https://img-eshop.cdn.nintendo.net/i/e97bcbf37c9f9c4ce9b81520d41b30c1e8d8def74358120f759474f3d29af8ce.jpg",
		"https://img-eshop.cdn.nintendo.net/i/3b7d9c23d5e85e3259f046e5002e6d576f815eb7c9f1403944f1f3d0159540b7.jpg"
	],
	"releaseDate": 20231214,
	"category": [
		"Adventure",
		"Platformer",
		"Action",
		"Other"
	],
	"intro": "Raccoo Venture is a 3D platformer that brings the nostalgia of the 90s into a playful, puzzle-filled world inspired by the great classics.",
	"description": "Defeat different enemies and challenges in this spiritual successor to the 3D platform genre. Find new ways to customize the hero, and discover new friends who will help you on your journey to retrieve the holy relics.\n\nDiscover your true destiny through a world full of magic and secret items. Save the harmony of the world and prevent chaos from returning to the land of Verta. But for that, many puzzles and the most unusual enemies will cross your path.\n\nResources:\n- Collect memorable Special Costumes that will give new looks and customize our esteemed hero.\n- Find the answers to the mysteries on your way, expanding new horizons in this magical land.\n- Simple gameplay\n- Stylized graphic with excellent animations\n- Numerous puzzles and secrets across maps.",
	"languages": [
		"en",
		"pt",
		"es",
		"de"
	],
	"numberOfPlayers": 1,
	"size": "2.65 GiB"
}