{
	"bannerUrl": "https://img-eshop.cdn.nintendo.net/i/4c1d48e1a5caff0dd79ffa75330865371a0680cccfa353883c327e1f84279af2.jpg",
	"iconUrl": "https://img-eshop.cdn.nintendo.net/i/8f09fbe746c114a732ff305ff678d0179e779241541e4e6d73349f0be16d4ae0.jpg",
	"publisher": "Contrast Games",
	"screenshots": [
		"https://img-eshop.cdn.nintendo.net/i/8690b464bb769fa77cbc399fe9830abee9b72685588592358641b5be97a1bbe7.jpg",
		"https://img-eshop.cdn.nintendo.net/i/2bc903db7fc3a1224a8ab8e54f1fe8fe5a7642408595502d3542347d0f0b6d2c.jpg",
		"https://img-eshop.cdn.nintendo.net/i/651e0ef70beeacb4370eb68acfac1947800aa0153f06dc7d068b9f0f444c6b5a.jpg",
		"https://img-eshop.cdn.nintendo.net/i/6fe9ad5aeb0459de101dfaadcfd8ac04ca0ac9f240af17d98b62c1e06dc36517.jpg",
		"https://img-eshop.cdn.nintendo.net/i/38fc0ae284e8303d53f2ed709a20c20fef14c4464badab17befb957a60782aee.jpg",
		"https://img-eshop.cdn.nintendo.net/i/7c29e702e9c7ead793d892a330e6ad67faa37ea707044a47b81377d4dd5c41b9.jpg"
	],
	"releaseDate": 20260507,
	"category": [
		"Adventure",
		"Simulation",
		"Other"
	],
	"intro": "First-person, Psychological Horror, Indie, Surreal, Gore, Singleplayer",
	"description": "Chorus of Carcosa is a psychological horror game inspired by the classic horror fiction of 'The King in Yellow' collection by R. W. Chambers. You play as a sculptor who is forced to abandon his place of comfort one night, when a blood-soaked neighbor knocks on his door.\n\nExperience the fear of facing the unknown. \nSurvive an ever-changing decrepit apartment building filled with dangers and mysteries... Without making a sound! Or THEY will hear you\u2026\n\nSolve the mystery of an alternate reality.\nA twisted realm fills the space around you. Are all of these changes real? Or are they just nightmarish hallucinations?\n\nYou can flee, but escape is an illusion.\nThey have found you and there's no turning back now. Perhaps, it\u2019s sometimes wiser to embrace the surrounding madness and stare right back into its eyes.",
	"languages": [
		"ja",
		"en",
		"pt",
		"es",
		"fr",
		"de",
		"it",
		"ru"
	],
	"numberOfPlayers": 1,
	"rating": 17,
	"ratingContent": [
		"Blood and Gore",
		"Intense Violence",
		"Strong Language",
		"Suggestive Themes"
	],
	"dlcs": [],
	"size": "1.32 GiB"
}